[
  {
    "timestamp": "2026-02-18T23:49:19.187368",
    "health_score": 70,
    "grade": "C",
    "summary": {
      "total": 99,
      "passed": 57,
      "failed": 2,
      "warned": 22,
      "info": 18
    },
    "critical_count": 0
  },
  {
    "timestamp": "2026-02-18T23:50:16.859221",
    "health_score": 70,
    "grade": "C",
    "summary": {
      "total": 99,
      "passed": 57,
      "failed": 2,
      "warned": 22,
      "info": 18
    },
    "critical_count": 0
  },
  {
    "timestamp": "2026-02-18T23:52:18.018233",
    "health_score": 84,
    "grade": "B",
    "summary": {
      "total": 99,
      "passed": 68,
      "failed": 0,
      "warned": 13,
      "info": 18
    },
    "critical_count": 0
  },
  {
    "timestamp": "2026-02-18T23:52:59.099719",
    "health_score": 86,
    "grade": "B",
    "summary": {
      "total": 99,
      "passed": 70,
      "failed": 0,
      "warned": 11,
      "info": 18
    },
    "critical_count": 0
  },
  {
    "timestamp": "2026-02-19T00:12:35.669826",
    "health_score": 86,
    "grade": "B",
    "summary": {
      "total": 99,
      "passed": 70,
      "failed": 0,
      "warned": 11,
      "info": 18
    },
    "critical_count": 0
  },
  {
    "timestamp": "2026-02-19T00:12:35.907734",
    "health_score": 86,
    "grade": "B",
    "summary": {
      "total": 99,
      "passed": 70,
      "failed": 0,
      "warned": 11,
      "info": 18
    },
    "critical_count": 0
  },
  {
    "timestamp": "2026-02-19T08:17:47.298087",
    "health_score": 85,
    "grade": "B",
    "summary": {
      "total": 100,
      "passed": 69,
      "failed": 1,
      "warned": 11,
      "info": 19
    },
    "critical_count": 0
  },
  {
    "timestamp": "2026-02-19T08:17:56.196420",
    "health_score": 85,
    "grade": "B",
    "summary": {
      "total": 100,
      "passed": 69,
      "failed": 1,
      "warned": 11,
      "info": 19
    },
    "critical_count": 0
  },
  {
    "timestamp": "2026-02-19T08:20:55.251988",
    "health_score": 85,
    "grade": "B",
    "summary": {
      "total": 100,
      "passed": 69,
      "failed": 1,
      "warned": 11,
      "info": 19
    },
    "critical_count": 0
  },
  {
    "timestamp": "2026-02-19T08:20:55.429066",
    "health_score": 85,
    "grade": "B",
    "summary": {
      "total": 100,
      "passed": 69,
      "failed": 1,
      "warned": 11,
      "info": 19
    },
    "critical_count": 0
  },
  {
    "timestamp": "2026-02-19T08:20:55.582048",
    "health_score": 85,
    "grade": "B",
    "summary": {
      "total": 100,
      "passed": 69,
      "failed": 1,
      "warned": 11,
      "info": 19
    },
    "critical_count": 0
  },
  {
    "timestamp": "2026-02-19T08:22:18.594790",
    "health_score": 85,
    "grade": "B",
    "summary": {
      "total": 100,
      "passed": 69,
      "failed": 1,
      "warned": 11,
      "info": 19
    },
    "critical_count": 0
  },
  {
    "timestamp": "2026-02-19T08:22:18.745227",
    "health_score": 85,
    "grade": "B",
    "summary": {
      "total": 100,
      "passed": 69,
      "failed": 1,
      "warned": 11,
      "info": 19
    },
    "critical_count": 0
  },
  {
    "timestamp": "2026-02-19T08:22:18.934964",
    "health_score": 85,
    "grade": "B",
    "summary": {
      "total": 100,
      "passed": 69,
      "failed": 1,
      "warned": 11,
      "info": 19
    },
    "critical_count": 0
  },
  {
    "timestamp": "2026-02-19T08:22:33.642340",
    "health_score": 85,
    "grade": "B",
    "summary": {
      "total": 100,
      "passed": 69,
      "failed": 1,
      "warned": 11,
      "info": 19
    },
    "critical_count": 0
  },
  {
    "timestamp": "2026-02-19T08:22:46.871144",
    "health_score": 85,
    "grade": "B",
    "summary": {
      "total": 100,
      "passed": 69,
      "failed": 1,
      "warned": 11,
      "info": 19
    },
    "critical_count": 0
  },
  {
    "timestamp": "2026-02-19T08:24:48.921624",
    "health_score": 85,
    "grade": "B",
    "summary": {
      "total": 100,
      "passed": 69,
      "failed": 1,
      "warned": 11,
      "info": 19
    },
    "critical_count": 0
  },
  {
    "timestamp": "2026-02-19T08:24:49.064778",
    "health_score": 85,
    "grade": "B",
    "summary": {
      "total": 100,
      "passed": 69,
      "failed": 1,
      "warned": 11,
      "info": 19
    },
    "critical_count": 0
  },
  {
    "timestamp": "2026-02-19T08:24:49.242054",
    "health_score": 85,
    "grade": "B",
    "summary": {
      "total": 100,
      "passed": 69,
      "failed": 1,
      "warned": 11,
      "info": 19
    },
    "critical_count": 0
  },
  {
    "timestamp": "2026-02-19T08:25:26.051007",
    "health_score": 85,
    "grade": "B",
    "summary": {
      "total": 100,
      "passed": 69,
      "failed": 1,
      "warned": 11,
      "info": 19
    },
    "critical_count": 0
  },
  {
    "timestamp": "2026-02-19T08:25:26.235710",
    "health_score": 85,
    "grade": "B",
    "summary": {
      "total": 100,
      "passed": 69,
      "failed": 1,
      "warned": 11,
      "info": 19
    },
    "critical_count": 0
  },
  {
    "timestamp": "2026-02-19T08:25:26.401037",
    "health_score": 85,
    "grade": "B",
    "summary": {
      "total": 100,
      "passed": 69,
      "failed": 1,
      "warned": 11,
      "info": 19
    },
    "critical_count": 0
  },
  {
    "timestamp": "2026-02-19T08:30:25.668221",
    "health_score": 85,
    "grade": "B",
    "summary": {
      "total": 100,
      "passed": 69,
      "failed": 1,
      "warned": 11,
      "info": 19
    },
    "critical_count": 0
  },
  {
    "timestamp": "2026-02-21T20:46:22.395211",
    "health_score": 84,
    "grade": "B",
    "summary": {
      "total": 111,
      "passed": 72,
      "failed": 3,
      "warned": 11,
      "info": 25
    },
    "critical_count": 0
  },
  {
    "timestamp": "2026-02-21T20:47:57.529268",
    "health_score": 84,
    "grade": "B",
    "summary": {
      "total": 111,
      "passed": 72,
      "failed": 3,
      "warned": 11,
      "info": 25
    },
    "critical_count": 0
  },
  {
    "timestamp": "2026-02-22T01:32:04.083383",
    "health_score": 87,
    "grade": "B",
    "summary": {
      "total": 110,
      "passed": 79,
      "failed": 2,
      "warned": 10,
      "info": 19
    },
    "critical_count": 0
  },
  {
    "timestamp": "2026-02-22T01:32:04.347523",
    "health_score": 87,
    "grade": "B",
    "summary": {
      "total": 110,
      "passed": 79,
      "failed": 2,
      "warned": 10,
      "info": 19
    },
    "critical_count": 0
  },
  {
    "timestamp": "2026-02-22T01:32:04.553863",
    "health_score": 87,
    "grade": "B",
    "summary": {
      "total": 110,
      "passed": 79,
      "failed": 2,
      "warned": 10,
      "info": 19
    },
    "critical_count": 0
  },
  {
    "timestamp": "2026-02-22T01:33:55.313070",
    "health_score": 87,
    "grade": "B",
    "summary": {
      "total": 110,
      "passed": 79,
      "failed": 2,
      "warned": 10,
      "info": 19
    },
    "critical_count": 0
  },
  {
    "timestamp": "2026-02-22T01:33:55.512627",
    "health_score": 87,
    "grade": "B",
    "summary": {
      "total": 110,
      "passed": 79,
      "failed": 2,
      "warned": 10,
      "info": 19
    },
    "critical_count": 0
  },
  {
    "timestamp": "2026-02-22T01:33:55.713996",
    "health_score": 87,
    "grade": "B",
    "summary": {
      "total": 110,
      "passed": 79,
      "failed": 2,
      "warned": 10,
      "info": 19
    },
    "critical_count": 0
  },
  {
    "timestamp": "2026-02-22T01:34:18.085944",
    "health_score": 87,
    "grade": "B",
    "summary": {
      "total": 110,
      "passed": 79,
      "failed": 2,
      "warned": 10,
      "info": 19
    },
    "critical_count": 0
  },
  {
    "timestamp": "2026-02-22T01:34:18.284031",
    "health_score": 87,
    "grade": "B",
    "summary": {
      "total": 110,
      "passed": 79,
      "failed": 2,
      "warned": 10,
      "info": 19
    },
    "critical_count": 0
  },
  {
    "timestamp": "2026-02-22T01:34:18.489806",
    "health_score": 87,
    "grade": "B",
    "summary": {
      "total": 110,
      "passed": 79,
      "failed": 2,
      "warned": 10,
      "info": 19
    },
    "critical_count": 0
  },
  {
    "timestamp": "2026-02-22T01:34:44.322772",
    "health_score": 87,
    "grade": "B",
    "summary": {
      "total": 110,
      "passed": 79,
      "failed": 2,
      "warned": 10,
      "info": 19
    },
    "critical_count": 0
  },
  {
    "timestamp": "2026-02-22T01:34:44.521958",
    "health_score": 87,
    "grade": "B",
    "summary": {
      "total": 110,
      "passed": 79,
      "failed": 2,
      "warned": 10,
      "info": 19
    },
    "critical_count": 0
  },
  {
    "timestamp": "2026-02-22T01:34:44.719677",
    "health_score": 87,
    "grade": "B",
    "summary": {
      "total": 110,
      "passed": 79,
      "failed": 2,
      "warned": 10,
      "info": 19
    },
    "critical_count": 0
  },
  {
    "timestamp": "2026-02-22T01:35:22.483370",
    "health_score": 87,
    "grade": "B",
    "summary": {
      "total": 110,
      "passed": 79,
      "failed": 2,
      "warned": 10,
      "info": 19
    },
    "critical_count": 0
  },
  {
    "timestamp": "2026-02-22T01:35:22.689795",
    "health_score": 87,
    "grade": "B",
    "summary": {
      "total": 110,
      "passed": 79,
      "failed": 2,
      "warned": 10,
      "info": 19
    },
    "critical_count": 0
  },
  {
    "timestamp": "2026-02-22T01:35:22.913143",
    "health_score": 87,
    "grade": "B",
    "summary": {
      "total": 110,
      "passed": 79,
      "failed": 2,
      "warned": 10,
      "info": 19
    },
    "critical_count": 0
  },
  {
    "timestamp": "2026-02-22T01:35:46.978623",
    "health_score": 87,
    "grade": "B",
    "summary": {
      "total": 110,
      "passed": 79,
      "failed": 2,
      "warned": 10,
      "info": 19
    },
    "critical_count": 0
  },
  {
    "timestamp": "2026-02-22T01:35:47.176324",
    "health_score": 87,
    "grade": "B",
    "summary": {
      "total": 110,
      "passed": 79,
      "failed": 2,
      "warned": 10,
      "info": 19
    },
    "critical_count": 0
  },
  {
    "timestamp": "2026-02-22T01:35:47.381379",
    "health_score": 87,
    "grade": "B",
    "summary": {
      "total": 110,
      "passed": 79,
      "failed": 2,
      "warned": 10,
      "info": 19
    },
    "critical_count": 0
  },
  {
    "timestamp": "2026-02-22T01:36:13.480422",
    "health_score": 87,
    "grade": "B",
    "summary": {
      "total": 110,
      "passed": 79,
      "failed": 2,
      "warned": 10,
      "info": 19
    },
    "critical_count": 0
  },
  {
    "timestamp": "2026-02-22T01:36:13.682213",
    "health_score": 87,
    "grade": "B",
    "summary": {
      "total": 110,
      "passed": 79,
      "failed": 2,
      "warned": 10,
      "info": 19
    },
    "critical_count": 0
  },
  {
    "timestamp": "2026-02-22T01:36:13.881531",
    "health_score": 87,
    "grade": "B",
    "summary": {
      "total": 110,
      "passed": 79,
      "failed": 2,
      "warned": 10,
      "info": 19
    },
    "critical_count": 0
  },
  {
    "timestamp": "2026-02-22T01:39:40.202727",
    "health_score": 87,
    "grade": "B",
    "summary": {
      "total": 110,
      "passed": 79,
      "failed": 2,
      "warned": 10,
      "info": 19
    },
    "critical_count": 0
  },
  {
    "timestamp": "2026-02-22T01:39:40.396969",
    "health_score": 87,
    "grade": "B",
    "summary": {
      "total": 110,
      "passed": 79,
      "failed": 2,
      "warned": 10,
      "info": 19
    },
    "critical_count": 0
  },
  {
    "timestamp": "2026-02-22T01:39:40.588679",
    "health_score": 87,
    "grade": "B",
    "summary": {
      "total": 110,
      "passed": 79,
      "failed": 2,
      "warned": 10,
      "info": 19
    },
    "critical_count": 0
  },
  {
    "timestamp": "2026-02-22T03:50:01.516770",
    "health_score": 87,
    "grade": "B",
    "summary": {
      "total": 110,
      "passed": 79,
      "failed": 2,
      "warned": 10,
      "info": 19
    },
    "critical_count": 0
  },
  {
    "timestamp": "2026-02-22T03:50:01.718010",
    "health_score": 87,
    "grade": "B",
    "summary": {
      "total": 110,
      "passed": 79,
      "failed": 2,
      "warned": 10,
      "info": 19
    },
    "critical_count": 0
  },
  {
    "timestamp": "2026-02-22T03:50:01.905897",
    "health_score": 87,
    "grade": "B",
    "summary": {
      "total": 110,
      "passed": 79,
      "failed": 2,
      "warned": 10,
      "info": 19
    },
    "critical_count": 0
  },
  {
    "timestamp": "2026-02-22T03:52:05.483663",
    "health_score": 87,
    "grade": "B",
    "summary": {
      "total": 110,
      "passed": 79,
      "failed": 2,
      "warned": 10,
      "info": 19
    },
    "critical_count": 0
  },
  {
    "timestamp": "2026-02-22T03:52:05.678265",
    "health_score": 87,
    "grade": "B",
    "summary": {
      "total": 110,
      "passed": 79,
      "failed": 2,
      "warned": 10,
      "info": 19
    },
    "critical_count": 0
  },
  {
    "timestamp": "2026-02-22T03:52:05.865049",
    "health_score": 87,
    "grade": "B",
    "summary": {
      "total": 110,
      "passed": 79,
      "failed": 2,
      "warned": 10,
      "info": 19
    },
    "critical_count": 0
  },
  {
    "timestamp": "2026-02-22T03:54:08.710973",
    "health_score": 87,
    "grade": "B",
    "summary": {
      "total": 110,
      "passed": 79,
      "failed": 2,
      "warned": 10,
      "info": 19
    },
    "critical_count": 0
  },
  {
    "timestamp": "2026-02-22T03:54:08.893892",
    "health_score": 87,
    "grade": "B",
    "summary": {
      "total": 110,
      "passed": 79,
      "failed": 2,
      "warned": 10,
      "info": 19
    },
    "critical_count": 0
  },
  {
    "timestamp": "2026-02-22T03:54:09.065277",
    "health_score": 87,
    "grade": "B",
    "summary": {
      "total": 110,
      "passed": 79,
      "failed": 2,
      "warned": 10,
      "info": 19
    },
    "critical_count": 0
  },
  {
    "timestamp": "2026-02-22T03:54:40.260746",
    "health_score": 87,
    "grade": "B",
    "summary": {
      "total": 110,
      "passed": 79,
      "failed": 2,
      "warned": 10,
      "info": 19
    },
    "critical_count": 0
  },
  {
    "timestamp": "2026-02-22T03:54:40.431444",
    "health_score": 87,
    "grade": "B",
    "summary": {
      "total": 110,
      "passed": 79,
      "failed": 2,
      "warned": 10,
      "info": 19
    },
    "critical_count": 0
  },
  {
    "timestamp": "2026-02-22T03:54:40.630372",
    "health_score": 87,
    "grade": "B",
    "summary": {
      "total": 110,
      "passed": 79,
      "failed": 2,
      "warned": 10,
      "info": 19
    },
    "critical_count": 0
  },
  {
    "timestamp": "2026-02-22T04:08:41.975841",
    "health_score": 87,
    "grade": "B",
    "summary": {
      "total": 110,
      "passed": 79,
      "failed": 2,
      "warned": 10,
      "info": 19
    },
    "critical_count": 0
  },
  {
    "timestamp": "2026-02-22T04:08:42.146864",
    "health_score": 87,
    "grade": "B",
    "summary": {
      "total": 110,
      "passed": 79,
      "failed": 2,
      "warned": 10,
      "info": 19
    },
    "critical_count": 0
  },
  {
    "timestamp": "2026-02-22T04:08:42.372483",
    "health_score": 87,
    "grade": "B",
    "summary": {
      "total": 110,
      "passed": 79,
      "failed": 2,
      "warned": 10,
      "info": 19
    },
    "critical_count": 0
  },
  {
    "timestamp": "2026-02-22T05:19:14.139320",
    "health_score": 85,
    "grade": "B",
    "summary": {
      "total": 111,
      "passed": 76,
      "failed": 2,
      "warned": 11,
      "info": 22
    },
    "critical_count": 0
  },
  {
    "timestamp": "2026-02-22T05:44:26.637238",
    "health_score": 86,
    "grade": "B",
    "summary": {
      "total": 110,
      "passed": 78,
      "failed": 2,
      "warned": 11,
      "info": 19
    },
    "critical_count": 0
  },
  {
    "timestamp": "2026-02-22T05:44:26.843834",
    "health_score": 86,
    "grade": "B",
    "summary": {
      "total": 110,
      "passed": 78,
      "failed": 2,
      "warned": 11,
      "info": 19
    },
    "critical_count": 0
  },
  {
    "timestamp": "2026-02-22T05:44:27.119287",
    "health_score": 86,
    "grade": "B",
    "summary": {
      "total": 110,
      "passed": 78,
      "failed": 2,
      "warned": 11,
      "info": 19
    },
    "critical_count": 0
  },
  {
    "timestamp": "2026-02-22T05:44:45.196651",
    "health_score": 84,
    "grade": "B",
    "summary": {
      "total": 111,
      "passed": 75,
      "failed": 2,
      "warned": 12,
      "info": 22
    },
    "critical_count": 0
  },
  {
    "timestamp": "2026-02-22T20:48:17.797869",
    "health_score": 96,
    "grade": "A",
    "summary": {
      "total": 28,
      "passed": 26,
      "failed": 1,
      "warned": 0,
      "info": 1
    },
    "critical_count": 0
  },
  {
    "timestamp": "2026-02-22T21:07:29.323628",
    "health_score": 96,
    "grade": "A",
    "summary": {
      "total": 28,
      "passed": 26,
      "failed": 1,
      "warned": 0,
      "info": 1
    },
    "critical_count": 0
  },
  {
    "timestamp": "2026-02-22T21:08:15.032407",
    "health_score": 87,
    "grade": "B",
    "summary": {
      "total": 110,
      "passed": 79,
      "failed": 2,
      "warned": 10,
      "info": 19
    },
    "critical_count": 0
  },
  {
    "timestamp": "2026-02-22T21:08:15.375681",
    "health_score": 87,
    "grade": "B",
    "summary": {
      "total": 110,
      "passed": 79,
      "failed": 2,
      "warned": 10,
      "info": 19
    },
    "critical_count": 0
  },
  {
    "timestamp": "2026-02-22T21:08:15.632769",
    "health_score": 87,
    "grade": "B",
    "summary": {
      "total": 110,
      "passed": 79,
      "failed": 2,
      "warned": 10,
      "info": 19
    },
    "critical_count": 0
  },
  {
    "timestamp": "2026-02-22T21:08:22.032810",
    "health_score": 96,
    "grade": "A",
    "summary": {
      "total": 28,
      "passed": 26,
      "failed": 1,
      "warned": 0,
      "info": 1
    },
    "critical_count": 0
  },
  {
    "timestamp": "2026-02-22T21:12:48.625271",
    "health_score": 87,
    "grade": "B",
    "summary": {
      "total": 110,
      "passed": 79,
      "failed": 2,
      "warned": 10,
      "info": 19
    },
    "critical_count": 0
  },
  {
    "timestamp": "2026-02-22T21:12:48.955763",
    "health_score": 87,
    "grade": "B",
    "summary": {
      "total": 110,
      "passed": 79,
      "failed": 2,
      "warned": 10,
      "info": 19
    },
    "critical_count": 0
  },
  {
    "timestamp": "2026-02-22T21:12:49.225287",
    "health_score": 87,
    "grade": "B",
    "summary": {
      "total": 110,
      "passed": 79,
      "failed": 2,
      "warned": 10,
      "info": 19
    },
    "critical_count": 0
  },
  {
    "timestamp": "2026-02-22T21:12:56.069724",
    "health_score": 96,
    "grade": "A",
    "summary": {
      "total": 28,
      "passed": 26,
      "failed": 1,
      "warned": 0,
      "info": 1
    },
    "critical_count": 0
  },
  {
    "timestamp": "2026-02-22T21:44:18.327177",
    "health_score": 96,
    "grade": "A",
    "summary": {
      "total": 28,
      "passed": 26,
      "failed": 1,
      "warned": 0,
      "info": 1
    },
    "critical_count": 0
  },
  {
    "timestamp": "2026-02-22T21:47:27.665822",
    "health_score": 96,
    "grade": "A",
    "summary": {
      "total": 28,
      "passed": 26,
      "failed": 1,
      "warned": 0,
      "info": 1
    },
    "critical_count": 0
  },
  {
    "timestamp": "2026-02-22T22:03:23.704688",
    "health_score": 96,
    "grade": "A",
    "summary": {
      "total": 28,
      "passed": 26,
      "failed": 1,
      "warned": 0,
      "info": 1
    },
    "critical_count": 0
  },
  {
    "timestamp": "2026-02-22T22:09:08.726923",
    "health_score": 96,
    "grade": "A",
    "summary": {
      "total": 28,
      "passed": 26,
      "failed": 1,
      "warned": 0,
      "info": 1
    },
    "critical_count": 0
  },
  {
    "timestamp": "2026-02-22T22:12:34.028288",
    "health_score": 96,
    "grade": "A",
    "summary": {
      "total": 28,
      "passed": 26,
      "failed": 1,
      "warned": 0,
      "info": 1
    },
    "critical_count": 0
  },
  {
    "timestamp": "2026-02-22T22:15:53.491808",
    "health_score": 96,
    "grade": "A",
    "summary": {
      "total": 28,
      "passed": 26,
      "failed": 1,
      "warned": 0,
      "info": 1
    },
    "critical_count": 0
  },
  {
    "timestamp": "2026-02-22T22:16:12.736361",
    "health_score": 87,
    "grade": "B",
    "summary": {
      "total": 111,
      "passed": 79,
      "failed": 2,
      "warned": 10,
      "info": 20
    },
    "critical_count": 0
  },
  {
    "timestamp": "2026-02-22T22:16:13.018741",
    "health_score": 87,
    "grade": "B",
    "summary": {
      "total": 111,
      "passed": 79,
      "failed": 2,
      "warned": 10,
      "info": 20
    },
    "critical_count": 0
  },
  {
    "timestamp": "2026-02-22T22:16:13.235445",
    "health_score": 87,
    "grade": "B",
    "summary": {
      "total": 111,
      "passed": 79,
      "failed": 2,
      "warned": 10,
      "info": 20
    },
    "critical_count": 0
  },
  {
    "timestamp": "2026-02-22T22:38:42.361864",
    "health_score": 96,
    "grade": "A",
    "summary": {
      "total": 28,
      "passed": 26,
      "failed": 1,
      "warned": 0,
      "info": 1
    },
    "critical_count": 0
  },
  {
    "timestamp": "2026-02-22T22:38:59.883701",
    "health_score": 87,
    "grade": "B",
    "summary": {
      "total": 111,
      "passed": 79,
      "failed": 2,
      "warned": 10,
      "info": 20
    },
    "critical_count": 0
  },
  {
    "timestamp": "2026-02-22T22:39:00.113734",
    "health_score": 87,
    "grade": "B",
    "summary": {
      "total": 111,
      "passed": 79,
      "failed": 2,
      "warned": 10,
      "info": 20
    },
    "critical_count": 0
  },
  {
    "timestamp": "2026-02-22T22:39:00.310712",
    "health_score": 87,
    "grade": "B",
    "summary": {
      "total": 111,
      "passed": 79,
      "failed": 2,
      "warned": 10,
      "info": 20
    },
    "critical_count": 0
  },
  {
    "timestamp": "2026-02-22T22:43:49.851981",
    "health_score": 96,
    "grade": "A",
    "summary": {
      "total": 28,
      "passed": 26,
      "failed": 1,
      "warned": 0,
      "info": 1
    },
    "critical_count": 0
  },
  {
    "timestamp": "2026-02-22T22:44:09.201998",
    "health_score": 87,
    "grade": "B",
    "summary": {
      "total": 111,
      "passed": 79,
      "failed": 2,
      "warned": 10,
      "info": 20
    },
    "critical_count": 0
  },
  {
    "timestamp": "2026-02-22T22:44:09.392229",
    "health_score": 87,
    "grade": "B",
    "summary": {
      "total": 111,
      "passed": 79,
      "failed": 2,
      "warned": 10,
      "info": 20
    },
    "critical_count": 0
  },
  {
    "timestamp": "2026-02-22T22:44:09.578326",
    "health_score": 87,
    "grade": "B",
    "summary": {
      "total": 111,
      "passed": 79,
      "failed": 2,
      "warned": 10,
      "info": 20
    },
    "critical_count": 0
  },
  {
    "timestamp": "2026-02-22T22:56:23.566830",
    "health_score": 96,
    "grade": "A",
    "summary": {
      "total": 28,
      "passed": 26,
      "failed": 1,
      "warned": 0,
      "info": 1
    },
    "critical_count": 0
  },
  {
    "timestamp": "2026-02-22T22:56:49.569513",
    "health_score": 87,
    "grade": "B",
    "summary": {
      "total": 111,
      "passed": 79,
      "failed": 2,
      "warned": 10,
      "info": 20
    },
    "critical_count": 0
  },
  {
    "timestamp": "2026-02-22T22:56:49.807277",
    "health_score": 87,
    "grade": "B",
    "summary": {
      "total": 111,
      "passed": 79,
      "failed": 2,
      "warned": 10,
      "info": 20
    },
    "critical_count": 0
  },
  {
    "timestamp": "2026-02-22T22:56:50.037317",
    "health_score": 87,
    "grade": "B",
    "summary": {
      "total": 111,
      "passed": 79,
      "failed": 2,
      "warned": 10,
      "info": 20
    },
    "critical_count": 0
  }
]